mopidy_youtube/__init__.py
mopidy_youtube/backend.py
mopidy_youtube/comms.py
mopidy_youtube/converters.py
mopidy_youtube/data.py
mopidy_youtube/ext.conf
mopidy_youtube/frontend.py
mopidy_youtube/timeformat.py
mopidy_youtube/web.py
mopidy_youtube/youtube.py
mopidy_youtube/apis/__init__.py
mopidy_youtube/apis/json_paths.py
mopidy_youtube/apis/youtube_api.py
mopidy_youtube/apis/youtube_bs4api.py
mopidy_youtube/apis/youtube_japi.py
mopidy_youtube/apis/youtube_music.py
mopidy_youtube/apis/youtube_scrapi.py
mopidy_youtube/apis/ytm_item_to_video.py
mopidy_youtube/www/image.html
mopidy_youtube/www/index.html
Mopidy_YouTube-3.7.dist-info/LICENSE
Mopidy_YouTube-3.7.dist-info/METADATA
Mopidy_YouTube-3.7.dist-info/WHEEL
Mopidy_YouTube-3.7.dist-info/entry_points.txt
Mopidy_YouTube-3.7.dist-info/pbr.json
Mopidy_YouTube-3.7.dist-info/top_level.txt
Mopidy_YouTube-3.7.dist-info/RECORD
